<TextureAtlas imagePath="run.png">
	<SubTexture name="run0000" x="0" y="0" w="432" h="388"/>
	<SubTexture name="run0001" x="0" y="0" w="432" h="388"/>
	<SubTexture name="run0002" x="0" y="0" w="432" h="388"/>
	<SubTexture name="run0003" x="0" y="0" w="432" h="388"/>
	<SubTexture name="run0004" x="0" y="0" w="432" h="388"/>
	<SubTexture name="run0005" x="0" y="0" w="432" h="388"/>
	<SubTexture name="run0006" x="432" y="0" w="432" h="388"/>
	<SubTexture name="run0007" x="432" y="0" w="432" h="388"/>
	<SubTexture name="run0008" x="432" y="0" w="432" h="388"/>
	<SubTexture name="run0009" x="432" y="0" w="432" h="388"/>
	<SubTexture name="run0010" x="432" y="0" w="432" h="388"/>
	<SubTexture name="run0011" x="432" y="0" w="432" h="388"/>
	<SubTexture name="run0012" x="0" y="388" w="432" h="388"/>
	<SubTexture name="run0013" x="0" y="388" w="432" h="388"/>
	<SubTexture name="run0014" x="0" y="388" w="432" h="388"/>
	<SubTexture name="run0015" x="0" y="388" w="432" h="388"/>
	<SubTexture name="run0016" x="0" y="388" w="432" h="388"/>
	<SubTexture name="run0017" x="0" y="388" w="432" h="388"/>
	<SubTexture name="run0018" x="432" y="388" w="432" h="388"/>
	<SubTexture name="run0019" x="432" y="388" w="432" h="388"/>
	<SubTexture name="run0020" x="432" y="388" w="432" h="388"/>
	<SubTexture name="run0021" x="432" y="388" w="432" h="388"/>
	<SubTexture name="run0022" x="432" y="388" w="432" h="388"/>
	<SubTexture name="run0023" x="432" y="388" w="432" h="388"/>
</TextureAtlas>
